mlprep/__init__.py
mlprep/cli.py
mlprep/mlprep.cp310-win32.pyd
mlprep_rust-0.3.0.dist-info/METADATA
mlprep_rust-0.3.0.dist-info/WHEEL
mlprep_rust-0.3.0.dist-info/entry_points.txt
mlprep_rust-0.3.0.dist-info/RECORD
