Metadata-Version: 2.4
Name: mlprep-rust
Version: 0.3.0
Classifier: Programming Language :: Rust
Classifier: Programming Language :: Python :: Implementation :: CPython
Classifier: Programming Language :: Python :: Implementation :: PyPy
Classifier: Programming Language :: Python :: 3.10
Classifier: Programming Language :: Python :: 3.11
Classifier: Programming Language :: Python :: 3.12
Classifier: License :: OSI Approved :: MIT License
Classifier: Topic :: Scientific/Engineering :: Artificial Intelligence
Classifier: Topic :: Scientific/Engineering :: Information Analysis
Requires-Dist: polars>=1.0.0
Requires-Dist: pytest>=7.4.0 ; extra == 'dev'
Requires-Dist: ruff>=0.1.0 ; extra == 'dev'
Provides-Extra: dev
Summary: High-performance no-code data preprocessing engine
Home-Page: https://github.com/takurot/mlprep
Author-email: Takuro Wada <public@takuro.t>
Requires-Python: >=3.10
